vivado/vivado.ip_user_files/ip/fp16_subtract/fp16_subtract_stub.v
// Copyright 1986-2022 Xilinx, Inc. All Rights Reserved.
// --------------------------------------------------------------------------------
// Tool Version: Vivado v.2022.1 (lin64) Build 3526262 Mon Apr 18 15:47:01 MDT 2022
// Date        : Thu Aug 21 12:39:56 2025
// Host        : ug51 running 64-bit Debian GNU/Linux 12 (bookworm)
// Command     : write_verilog -force -mode synth_stub
//               /nfs/ug/homes-2/c/cheng520/ISML/GAP_SCI/vivado/vivado.gen/sources_1/ip/fp16_subtract/fp16_subtract_stub.v
// Design      : fp16_subtract
// Purpose     : Stub declaration of top-level module interface
// Device      : xcvu13p_CIV-fsga2577-1-i
// --------------------------------------------------------------------------------

// This empty module with port declaration file causes synthesis tools to infer a black box for IP.
// The synthesis directives are for Synopsys Synplify support to prevent IO buffer insertion.
// Please paste the declaration into a Verilog source file or add the file as an additional source.
(* X_CORE_INFO = "floating_point_v7_1_14,Vivado 2022.1" *)
module fp16_subtract(aclk, aresetn, s_axis_a_tvalid, s_axis_a_tdata, 
  s_axis_b_tvalid, s_axis_b_tdata, m_axis_result_tvalid, m_axis_result_tdata, 
  m_axis_result_tuser)
/* synthesis syn_black_box black_box_pad_pin="aclk,aresetn,s_axis_a_tvalid,s_axis_a_tdata[15:0],s_axis_b_tvalid,s_axis_b_tdata[15:0],m_axis_result_tvalid,m_axis_result_tdata[15:0],m_axis_result_tuser[2:0]" */;
  input aclk;
  input aresetn;
  input s_axis_a_tvalid;
  input [15:0]s_axis_a_tdata;
  input s_axis_b_tvalid;
  input [15:0]s_axis_b_tdata;
  output m_axis_result_tvalid;
  output [15:0]m_axis_result_tdata;
  output [2:0]m_axis_result_tuser;
endmodule

tests/top/testfixture_1.sv
// Test floating point subtraction IP

`timescale 1 ns / 1 ps
`define PORT_SIZE 32

module testfixture;

reg clk = 1'b0;
reg rst_n = 1'b0;
reg f_num = 2;

initial forever #10 clk = ~clk;
initial #60 rst_n = ~rst_n;

reg [15:0] a_in, b_in;
reg a_valid, b_valid;
wire r_valid;
wire [15:0] r_data;
wire [2:0] r_user;

fp16_subtract u_subtract(
	.aclk(clk),
	.aresetn(rst_n),
	.s_axis_a_tvalid(a_valid),
	.s_axis_a_tdata(a_in),
	.s_axis_b_tvalid(b_valid),
	.s_axis_b_tdata(b_in),
	.m_axis_result_tvalid(r_valid),
	.m_axis_result_tdata(r_data),
	.m_axis_result_tuser(r_user)
);

initial begin
	//$fsdbDumpfile("test_000.fsdb");
	//$fsdbDumpvars;
	$dumpfile("test_000.vcd");
	$dumpvars;
end

initial begin
	a_in <= 16'h3cf0;
	b_in <= 16'h4d56;
	// a_valid <= 1'b0;
	// b_valid <= 1'b0;
	// #120
	a_valid <= 1'b1;
	b_valid <= 1'b1;
	#60
	a_in <= 16'h7935;
	b_in <= 16'h7502;
	#20
	a_in <= 16'h770d;
	b_in <= 16'h7a7e;
	#20
	a_in <= 16'hf758;
	b_in <= 16'h69a0;
	#20
	a_in <= 16'h78da;
	b_in <= 16'h7aa4;
	#20
	a_in <= 16'hf879;
	b_in <= 16'hf45b;
	#20
	a_in <= 16'he73c;
	b_in <= 16'h781b;
	#20
	a_in <= 16'h77d3;
	b_in <= 16'h7968;
	#20
	a_in <= 16'hf8a3;
	b_in <= 16'h7741;
	#20
	a_in <= 16'h785a;
	b_in <= 16'hfac3;
	#20
	a_in <= 16'h73f4;
	b_in <= 16'h7ac3;
	#20
	a_in <= 16'heb6e;
	b_in <= 16'hf94c;
	#20
	a_in <= 16'hfa5d;
	b_in <= 16'h76b9;
	#20
	a_in <= 16'h5429;
	b_in <= 16'h7913;
	#20
	a_in <= 16'h72c1;
	b_in <= 16'h7ae8;
	#20
	a_in <= 16'h7160;
	b_in <= 16'hfad0;
	#20
	a_in <= 16'hf8c6;
	b_in <= 16'h757b;
	#20
	a_in <= 16'hf3d3;
	b_in <= 16'hf89c;
	#20
	a_in <= 16'hf0c9;
	b_in <= 16'hf877;
	#20
	a_in <= 16'h788c;
	b_in <= 16'h7712;
	#20
	a_in <= 16'h7861;
	b_in <= 16'h77e5;
	#20
	#100_000;
	$finish;
end

endmodule

vivado/vivado.sim/sim_1/behav/xsim/test_000.vcd
$date
   Thu Aug 21 17:13:25 2025
$end
$version
  2022.1
$end
$timescale
  1ps
$end
$scope module testfixture $end
$var reg 1 ! clk $end
$var reg 1 " rst_n $end
$var reg 1 # f_num $end
$var reg 16 $ a_in [15:0] $end
$var reg 16 % b_in [15:0] $end
$var reg 1 & a_valid $end
$var reg 1 ' b_valid $end
$var wire 1 ( r_valid $end
$var wire 16 ) r_data [15:0] $end
$var wire 3 * r_user [2:0] $end
$scope module u_subtract $end
$var wire 1 + aclk $end
$var wire 1 , aresetn $end
$var wire 1 - s_axis_a_tvalid $end
$var wire 16 . s_axis_a_tdata [15:0] $end
$var wire 1 / s_axis_b_tvalid $end
$var wire 16 0 s_axis_b_tdata [15:0] $end
$var wire 1 ( m_axis_result_tvalid $end
$var wire 16 ) m_axis_result_tdata [15:0] $end
$var wire 3 * m_axis_result_tuser [2:0] $end
$upscope $end
$upscope $end
$enddefinitions $end
#0
$dumpvars
0!
0"
0#
b11110011110000 $
b100110101010110 %
1&
1'
0(
bx )
b0 *
0+
0,
1-
b11110011110000 .
1/
b100110101010110 0
$end
#10000
1!
b0 )
1+
#20000
0!
0+
#30000
1!
1+
#40000
0!
0+
#50000
1!
b1 *
1+
#60000
0!
1"
b111100100110101 $
b111010100000010 %
0+
1,
b111100100110101 .
b111010100000010 0
#70000
1!
b10000000000 )
b0 *
1+
#80000
0!
b111011100001101 $
b111101001111110 %
0+
b111011100001101 .
b111101001111110 0
#90000
1!
1+
#100000
0!
b1111011101011000 $
b110100110100000 %
0+
b1111011101011000 .
b110100110100000 0
#110000
1!
b0 )
1+
#120000
0!
b111100011011010 $
b111101010100100 %
0+
b111100011011010 .
b111101010100100 0
#130000
1!
1+
#140000
0!
b1111100001111001 $
b1111010001011011 %
0+
b1111100001111001 .
b1111010001011011 0
#150000
1!
1+
#160000
0!
b1110011100111100 $
b111100000011011 %
0+
b1110011100111100 .
b111100000011011 0
#170000
1!
1+
#180000
0!
b111011111010011 $
b111100101101000 %
0+
b111011111010011 .
b111100101101000 0
#190000
1!
b10000000000 )
1+
#200000
0!
b1111100010100011 $
b111011101000001 %
0+
b1111100010100011 .
b111011101000001 0
#210000
1!
b1100110100000111 )
1+
#220000
0!
b111100001011010 $
b1111101011000011 %
0+
b111100001011010 .
b1111101011000011 0
#230000
1!
1+
#240000
0!
b111001111110100 $
b111101011000011 %
0+
b111001111110100 .
b111101011000011 0
#250000
1!
1+
#260000
0!
b1110101101101110 $
b1111100101001100 %
0+
b1110101101101110 .
b1111100101001100 0
#270000
1!
b111010101101000 )
1+
#280000
0!
b1111101001011101 $
b111011010111001 %
0+
b1111101001011101 .
b111011010111001 0
#290000
1!
1(
b1111010111101111 )
1+
#300000
0!
b101010000101001 $
b111100100010011 %
0+
b101010000101001 .
b111100100010011 0
#310000
1!
b1111100000000110 )
1+
#320000
0!
b111001011000001 $
b111101011101000 %
0+
b111001011000001 .
b111101011101000 0
#330000
1!
b1111001100101000 )
1+
#340000
0!
b111000101100000 $
b1111101011010000 %
0+
b111000101100000 .
b1111101011010000 0
#350000
1!
b1111010010010111 )
1+
#360000
0!
b1111100011000110 $
b111010101111011 %
0+
b1111100011000110 .
b111010101111011 0
#370000
1!
b1111100001010101 )
1+
#380000
0!
b1111001111010011 $
b1111100010011100 %
0+
b1111001111010011 .
b1111100010011100 0
#390000
1!
b1111000111111010 )
1+
#400000
0!
b1111000011001001 $
b1111100001110111 %
0+
b1111000011001001 .
b1111100001110111 0
#410000
1!
b1111110000000000 )
b10 *
1+
#420000
0!
b111100010001100 $
b111011100010010 %
0+
b111100010001100 .
b111011100010010 0
#430000
1!
b111110000000000 )
1+
#440000
0!
b111100001100001 $
b111011111100101 %
0+
b111100001100001 .
b111011111100101 0
#450000
1!
b1111100011000110 )
b0 *
1+
#460000
0!
0+
#470000
1!
b111100011010101 )
1+
#480000
0!
0+
#490000
1!
b1111110000000000 )
b10 *
1+
#500000
0!
0+
#510000
1!
b1111100100010001 )
b0 *
1+
#520000
0!
0+
#530000
1!
b1111100100111000 )
1+
#540000
0!
0+
#550000
1!
b111110000000000 )
b10 *
1+
#560000
0!
0+
#570000
1!
b1111101110000100 )
b0 *
1+
#580000
0!
0+
#590000
1!
b111010101001110 )
1+
#600000
0!
0+
#610000
1!
b111011010001010 )
1+
#620000
0!
0+
#630000
1!
b111000000001100 )
1+
#640000
0!
0+
#650000
1!
b110101011101000 )
1+
